{
  "pages": {
    "splash_page": {
      "type": "splash",
      "style": {
        "background": {
          "backgroundColor": "green"
        },
        "logo": {
          "width": 64,
          "height": 64
        },
        "logoText": {
          "fontSize": 18,
          "fontFamily": "Helvetica Neue",
          "color": "white"
        }
      },
      "resources": {
        "logo": {
          "imageSrc": "foo.png"
        },
        "logoText": {
          "text": ""
        }
      },
      "transitions": {
        "*": "login_page"
      }
    },
    "login_page": {
      "type": "login",
      "style": {
        "pageBackground": {
          "backgroundColor": "blue"
        }
      },
      "resources": {},
      "transitions": {
        "*": "main_page"
      }
    },
    "main_page": {
      "type": "custom",
      "components": [
        {
          "type": "button",
          "layoutCell": 2,
          "text": "log out",
          "iconLayout": "right",
          "imageSrc": "foo.png",
          "eval": "foo",
          "style": {
            "border": {
              "boderWidth": "2",
              "borderColor": "red"
            },
            "text": {
              "color": "red"
            },
            "icon": {
              "width": "24",
              "height": "24"
            }
          }
        },
        {
          "type": "button",
          "layoutCell": 1,
          "text": "restart",
          "iconLayout": "left",
          "imageSrc": "bar.png",
          "eval": "bar",
          "style": {
            "border": {
              "boderWidth": "2",
              "borderColor": "green"
            },
            "text": {
              "color": "green"
            },
            "icon": {
              "width": "24",
              "height": "24"
            }
          }
        }
      ],
      "style": {},
      "layout": "2x1",
      "transitions": {
        "foo": "login_page",
        "bar": "splash_page"
      }
    }
  },
  "metaData": {
    "userID": 90123832
  }
}
